README.md
setup.py
migralite/__init__.py
migralite/main.py
migralite/utils.py
migralite.egg-info/PKG-INFO
migralite.egg-info/SOURCES.txt
migralite.egg-info/dependency_links.txt
migralite.egg-info/entry_points.txt
migralite.egg-info/requires.txt
migralite.egg-info/top_level.txt
test/test_main.py