Metadata-Version: 2.1
Name: migralite
Version: 0.0.18
Summary: migralite is a simple mysql migration tool (python3 only)
Home-page: https://github.com/qorzj/migralite
Author: qorzj
Author-email: inull@qq.com
License: MIT
Keywords: migralite mysql migrate
Platform: any
